wagtail_reusable_blocks/__init__.py
wagtail_reusable_blocks/apps.py
wagtail_reusable_blocks/cache.py
wagtail_reusable_blocks/conf.py
wagtail_reusable_blocks/signals.py
wagtail_reusable_blocks/urls.py
wagtail_reusable_blocks/wagtail_hooks.py
wagtail_reusable_blocks/widgets.py
wagtail_reusable_blocks/blocks/__init__.py
wagtail_reusable_blocks/blocks/chooser.py
wagtail_reusable_blocks/blocks/head_injection.py
wagtail_reusable_blocks/blocks/html.py
wagtail_reusable_blocks/blocks/image.py
wagtail_reusable_blocks/blocks/layout.py
wagtail_reusable_blocks/blocks/slot_fill.py
wagtail_reusable_blocks/locale/bg/LC_MESSAGES/django.mo
wagtail_reusable_blocks/locale/bg/LC_MESSAGES/django.po
wagtail_reusable_blocks/locale/de/LC_MESSAGES/django.mo
wagtail_reusable_blocks/locale/de/LC_MESSAGES/django.po
wagtail_reusable_blocks/locale/en/LC_MESSAGES/django.mo
wagtail_reusable_blocks/locale/en/LC_MESSAGES/django.po
wagtail_reusable_blocks/locale/fr/LC_MESSAGES/django.mo
wagtail_reusable_blocks/locale/fr/LC_MESSAGES/django.po
wagtail_reusable_blocks/locale/hu/LC_MESSAGES/django.mo
wagtail_reusable_blocks/locale/hu/LC_MESSAGES/django.po
wagtail_reusable_blocks/migrations/0001_initial.py
wagtail_reusable_blocks/migrations/0002_alter_reusableblock_slug.py
wagtail_reusable_blocks/migrations/0003_add_wagtail_mixins.py
wagtail_reusable_blocks/migrations/0004_add_reusableblock_to_content.py
wagtail_reusable_blocks/migrations/0005_add_head_injection_block.py
wagtail_reusable_blocks/migrations/__init__.py
wagtail_reusable_blocks/models/__init__.py
wagtail_reusable_blocks/models/reusable_block.py
wagtail_reusable_blocks/static/wagtail_reusable_blocks/js/slot-chooser.js
wagtail_reusable_blocks/templates/wagtail_reusable_blocks/preview.html
wagtail_reusable_blocks/templates/wagtail_reusable_blocks/reusable_block.html
wagtail_reusable_blocks/templates/wagtail_reusable_blocks/blocks/image.html
wagtail_reusable_blocks/templatetags/__init__.py
wagtail_reusable_blocks-0.7.2.dist-info/METADATA
wagtail_reusable_blocks-0.7.2.dist-info/WHEEL
wagtail_reusable_blocks-0.7.2.dist-info/licenses/LICENSE
wagtail_reusable_blocks-0.7.2.dist-info/RECORD
